simple_caching/__init__.py
simple_caching/cache.py
simple_caching/dict_memory.py
simple_caching/npy_fs.py
python_simple_caching-0.12.dist-info/LICENSE.txt
python_simple_caching-0.12.dist-info/METADATA
python_simple_caching-0.12.dist-info/WHEEL
python_simple_caching-0.12.dist-info/top_level.txt
python_simple_caching-0.12.dist-info/RECORD
