Metadata-Version: 2.1
Name: python-simple-caching
Version: 0.12
Summary: Simple caching library for python
Home-page: https://gitlab.com/mihaicristianpirvu/simple-caching/
Author: Mihai Cristian Pîrvu
Author-email: mihaicristianpirvu@gmail.com
License: WTFPL
Keywords: caching,cache
Platform: UNKNOWN
Classifier: Programming Language :: Python :: 3
Classifier: Operating System :: OS Independent
Requires-Python: >=3.8
License-File: LICENSE.txt
